cloud2zone/__init__.py
cloud2zone/cli.py
cloud2zone/utils.py
cloud2zone-0.1.2.dist-info/LICENSE
cloud2zone-0.1.2.dist-info/METADATA
cloud2zone-0.1.2.dist-info/WHEEL
cloud2zone-0.1.2.dist-info/entry_points.txt
cloud2zone-0.1.2.dist-info/top_level.txt
cloud2zone-0.1.2.dist-info/RECORD
