Metadata-Version: 2.1
Name: cloud2zone
Version: 0.1.2
Summary: Python module which allows you to export Libcloud DNS zone to the BIND zone file format
Home-page: https://github.com/glyph/cloud2zone/
Author: Tomaz Muraus
Author-email: tomaz+pypi@tomaz.me
Maintainer: Glyph Lefkowitz
Maintainer-email: glyph@glyph.im
License: Apache License (2.0)
Platform: UNKNOWN
Classifier: Development Status :: 4 - Beta
Classifier: Environment :: Console
Classifier: Intended Audience :: Developers
Classifier: Intended Audience :: System Administrators
Classifier: Operating System :: OS Independent
Classifier: License :: OSI Approved :: Apache Software License
Classifier: Programming Language :: Python
Classifier: Programming Language :: Python :: 3.10
Classifier: Topic :: Software Development :: Libraries :: Python Modules
License-File: LICENSE
Requires-Dist: apache-libcloud (>=0.13.1)
Requires-Dist: keyring
Requires-Dist: click
